{"Computability": [1, "/categories/computability/", {"posts": [{"date": "06/01/2014", "isodate": "2014-06-01T20:54:42+00:00", "title": "G53COM Computability \u53ef\u8ba1\u7b97\u6027 \u590d\u4e60\u7b14\u8bb0", "url": "/posts/g53com-computability-1314-revision-notes/"}]}], "Concurrency": [2, "/categories/concurrency/", {"posts": [{"date": "12/28/2015", "isodate": "2015-12-28T08:10:20+00:00", "title": "\u300aJava\u5e76\u53d1\u5b9e\u8df5\u300b\u603b\u7ed3\u4e8c\uff1a\u7ed3\u6784\u5316\u5e76\u53d1\u5e94\u7528\u7a0b\u5e8f", "url": "/posts/java-concurrency-2/"}, {"date": "12/28/2015", "isodate": "2015-12-28T07:50:12+00:00", "title": "\u300aJava\u5e76\u53d1\u5b9e\u8df5\u300b\u603b\u7ed3\u4e00\uff1a\u7ebf\u7a0b\u5b89\u5168\u57fa\u7840\u77e5\u8bc6", "url": "/posts/java-concurrency-1/"}]}], "JVM": [3, "/categories/jvm/", {"posts": [{"date": "12/28/2015", "isodate": "2015-12-28T10:09:30+00:00", "title": "Java\u7c7b\u52a0\u8f7d\u673a\u5236", "url": "/posts/java-class-loading/"}, {"date": "11/26/2015", "isodate": "2015-11-26T16:00:00+00:00", "title": "Java\u5783\u573e\u6536\u96c6\u6280\u672f", "url": "/posts/java-gc/"}, {"date": "11/26/2015", "isodate": "2015-11-26T15:40:00+00:00", "title": "Java\u52a8\u6001\u5185\u5b58\u5206\u914d", "url": "/posts/dynamic-memory-allocation/"}]}], "Java": [5, "/categories/java/", {"posts": [{"date": "12/28/2015", "isodate": "2015-12-28T10:09:30+00:00", "title": "Java\u7c7b\u52a0\u8f7d\u673a\u5236", "url": "/posts/java-class-loading/"}, {"date": "12/28/2015", "isodate": "2015-12-28T08:10:20+00:00", "title": "\u300aJava\u5e76\u53d1\u5b9e\u8df5\u300b\u603b\u7ed3\u4e8c\uff1a\u7ed3\u6784\u5316\u5e76\u53d1\u5e94\u7528\u7a0b\u5e8f", "url": "/posts/java-concurrency-2/"}, {"date": "12/28/2015", "isodate": "2015-12-28T07:50:12+00:00", "title": "\u300aJava\u5e76\u53d1\u5b9e\u8df5\u300b\u603b\u7ed3\u4e00\uff1a\u7ebf\u7a0b\u5b89\u5168\u57fa\u7840\u77e5\u8bc6", "url": "/posts/java-concurrency-1/"}, {"date": "11/26/2015", "isodate": "2015-11-26T16:00:00+00:00", "title": "Java\u5783\u573e\u6536\u96c6\u6280\u672f", "url": "/posts/java-gc/"}, {"date": "11/26/2015", "isodate": "2015-11-26T15:40:00+00:00", "title": "Java\u52a8\u6001\u5185\u5b58\u5206\u914d", "url": "/posts/dynamic-memory-allocation/"}]}], "Notes": [1, "/categories/notes/", {"posts": [{"date": "06/01/2014", "isodate": "2014-06-01T20:54:42+00:00", "title": "G53COM Computability \u53ef\u8ba1\u7b97\u6027 \u590d\u4e60\u7b14\u8bb0", "url": "/posts/g53com-computability-1314-revision-notes/"}]}]}